odoo/addons/l10n_cl_invoicing_policy/README.rst
odoo/addons/l10n_cl_invoicing_policy/__init__.py
odoo/addons/l10n_cl_invoicing_policy/__manifest__.py
odoo/addons/l10n_cl_invoicing_policy/i18n/es_CL.po
odoo/addons/l10n_cl_invoicing_policy/i18n/l10n_cl_invoicing_policy.pot
odoo/addons/l10n_cl_invoicing_policy/models/__init__.py
odoo/addons/l10n_cl_invoicing_policy/models/res_partner.py
odoo/addons/l10n_cl_invoicing_policy/readme/CONTRIBUTORS.rst
odoo/addons/l10n_cl_invoicing_policy/readme/DESCRIPTION.rst
odoo/addons/l10n_cl_invoicing_policy/readme/USAGE.rst
odoo/addons/l10n_cl_invoicing_policy/static/description/icon.png
odoo/addons/l10n_cl_invoicing_policy/static/description/index.html
odoo/addons/l10n_cl_invoicing_policy/views/res_partner.xml
odoo12_addon_l10n_cl_invoicing_policy-12.0.1.0.2.dist-info/METADATA
odoo12_addon_l10n_cl_invoicing_policy-12.0.1.0.2.dist-info/WHEEL
odoo12_addon_l10n_cl_invoicing_policy-12.0.1.0.2.dist-info/top_level.txt
odoo12_addon_l10n_cl_invoicing_policy-12.0.1.0.2.dist-info/RECORD
